biodetectron/__init__.py
biodetectron/data.py
biodetectron/datasets.py
biodetectron/eval.py
biodetectron/metrics.py
biodetectron/train.py
biodetectron/utils.py
biodetectron-0.1.0.dist-info/METADATA
biodetectron-0.1.0.dist-info/WHEEL
biodetectron-0.1.0.dist-info/top_level.txt
biodetectron-0.1.0.dist-info/RECORD
